[
{
    "_id": {
        "$oid": "857471e29fc5c9a85a7f8cfb"
    },
    "player_id": {"$oid": "p857471e29fc5c9a85a7f8cfb" },
    "hits": "35",
    "singles": "8",
    "doubles": "11",
    "triples": "8",
    "homeruns": "0",
    "plate_appearances": "105",
    "at_bats": "81"
},
{
    "_id": {
        "$oid": "547be8df469c122c6d2843cd"
    },
    "player_id": {"$oid": "p547be8df469c122c6d2843cd" },
    "hits": "95",
    "singles": "11",
    "doubles": "25",
    "triples": "18",
    "homeruns": "21",
    "plate_appearances": "120",
    "at_bats": "94"
},
{
    "_id": {
        "$oid": "7ed4322ab8257966bdd1dbc6"
    },
    "player_id": {"$oid": "p7ed4322ab8257966bdd1dbc6" },
    "hits": "74",
    "singles": "14",
    "doubles": "15",
    "triples": "8",
    "homeruns": "14",
    "plate_appearances": "102",
    "at_bats": "94"
},
{
    "_id": {
        "$oid": "4d6579f9324a2be1d3aaf2ad"
    },
    "player_id": {"$oid": "p4d6579f9324a2be1d3aaf2ad" },
    "hits": "34",
    "singles": "13",
    "doubles": "14",
    "triples": "17",
    "homeruns": "11",
    "plate_appearances": "114",
    "at_bats": "87"
},
{
    "_id": {
        "$oid": "7464351badaebfbda9982aa7"
    },
    "player_id": {"$oid": "p7464351badaebfbda9982aa7" },
    "hits": "42",
    "singles": "21",
    "doubles": "8",
    "triples": "7",
    "homeruns": "4",
    "plate_appearances": "106",
    "at_bats": "83"
},
{
    "_id": {
        "$oid": "e1fb551875ce62e55bffcd1b"
    },
    "player_id": {"$oid": "pe1fb551875ce62e55bffcd1b" },
    "hits": "6",
    "singles": "15",
    "doubles": "1",
    "triples": "20",
    "homeruns": "9",
    "plate_appearances": "114",
    "at_bats": "112"
},
{
    "_id": {
        "$oid": "dfe4ae6e66b36f29b8aef5cf"
    },
    "player_id": {"$oid": "pdfe4ae6e66b36f29b8aef5cf" },
    "hits": "95",
    "singles": "16",
    "doubles": "9",
    "triples": "6",
    "homeruns": "8",
    "plate_appearances": "104",
    "at_bats": "75"
},
{
    "_id": {
        "$oid": "7d69c34ff2fe87a78ddbd4ca"
    },
    "player_id": {"$oid": "p7d69c34ff2fe87a78ddbd4ca" },
    "hits": "37",
    "singles": "0",
    "doubles": "25",
    "triples": "21",
    "homeruns": "16",
    "plate_appearances": "105",
    "at_bats": "92"
},
{
    "_id": {
        "$oid": "565c38cb76ef53be776f5a9f"
    },
    "player_id": {"$oid": "p565c38cb76ef53be776f5a9f" },
    "hits": "23",
    "singles": "18",
    "doubles": "20",
    "triples": "0",
    "homeruns": "18",
    "plate_appearances": "111",
    "at_bats": "88"
},
{
    "_id": {
        "$oid": "99fc9dfd456a1edc92c96cd6"
    },
    "player_id": {"$oid": "p99fc9dfd456a1edc92c96cd6" },
    "hits": "76",
    "singles": "15",
    "doubles": "21",
    "triples": "12",
    "homeruns": "14",
    "plate_appearances": "105",
    "at_bats": "104"
},
{
    "_id": {
        "$oid": "98f221e22bffbad7fd27dcc8"
    },
    "player_id": {"$oid": "p98f221e22bffbad7fd27dcc8" },
    "hits": "83",
    "singles": "10",
    "doubles": "8",
    "triples": "5",
    "homeruns": "14",
    "plate_appearances": "120",
    "at_bats": "106"
},
{
    "_id": {
        "$oid": "eff444bed961a31d2fe41743"
    },
    "player_id": {"$oid": "peff444bed961a31d2fe41743" },
    "hits": "85",
    "singles": "4",
    "doubles": "10",
    "triples": "25",
    "homeruns": "23",
    "plate_appearances": "104",
    "at_bats": "103"
},
{
    "_id": {
        "$oid": "aeec6ff8d85dade75ab1a7e5"
    },
    "player_id": {"$oid": "paeec6ff8d85dade75ab1a7e5" },
    "hits": "74",
    "singles": "19",
    "doubles": "15",
    "triples": "23",
    "homeruns": "10",
    "plate_appearances": "112",
    "at_bats": "86"
},
{
    "_id": {
        "$oid": "ba7c1c98aa759ca433269da6"
    },
    "player_id": {"$oid": "pba7c1c98aa759ca433269da6" },
    "hits": "37",
    "singles": "22",
    "doubles": "14",
    "triples": "0",
    "homeruns": "22",
    "plate_appearances": "115",
    "at_bats": "109"
},
{
    "_id": {
        "$oid": "faad1ff3d994eaddfcedfe19"
    },
    "player_id": {"$oid": "pfaad1ff3d994eaddfcedfe19" },
    "hits": "50",
    "singles": "22",
    "doubles": "8",
    "triples": "6",
    "homeruns": "21",
    "plate_appearances": "102",
    "at_bats": "90"
},
{
    "_id": {
        "$oid": "e9c9e4cff88a8cdce2aead3b"
    },
    "player_id": {"$oid": "pe9c9e4cff88a8cdce2aead3b" },
    "hits": "55",
    "singles": "3",
    "doubles": "5",
    "triples": "10",
    "homeruns": "1",
    "plate_appearances": "117",
    "at_bats": "112"
},
{
    "_id": {
        "$oid": "26ecbcefde5cecdc33cfafcc"
    },
    "player_id": {"$oid": "p26ecbcefde5cecdc33cfafcc" },
    "hits": "28",
    "singles": "0",
    "doubles": "21",
    "triples": "13",
    "homeruns": "4",
    "plate_appearances": "108",
    "at_bats": "105"
},
{
    "_id": {
        "$oid": "8cfcec555f97fd4f9fa43edf"
    },
    "player_id": {"$oid": "p8cfcec555f97fd4f9fa43edf" },
    "hits": "55",
    "singles": "6",
    "doubles": "5",
    "triples": "8",
    "homeruns": "21",
    "plate_appearances": "106",
    "at_bats": "103"
},
{
    "_id": {
        "$oid": "cbde433dbc1fdcbc2ee96318"
    },
    "player_id": {"$oid": "pcbde433dbc1fdcbc2ee96318" },
    "hits": "20",
    "singles": "0",
    "doubles": "10",
    "triples": "4",
    "homeruns": "24",
    "plate_appearances": "110",
    "at_bats": "91"
},
{
    "_id": {
        "$oid": "ebeb3ba1ed4182ce38afdb9e"
    },
    "player_id": {"$oid": "pebeb3ba1ed4182ce38afdb9e" },
    "hits": "84",
    "singles": "4",
    "doubles": "11",
    "triples": "20",
    "homeruns": "9",
    "plate_appearances": "101",
    "at_bats": "82"
}]